Workbook

Sheet Dashboard
B2: IT Asset & Helpdesk Management System
B3: Built by Zohaib Yousaf — IT Manager | info@zohaibyousaf.com | All figures below are live Excel formulas.
B5: Total Assets | E5: Open / Active Tickets | H5: Device Compliance %
B6: =COUNTA(Assets!A2:A500) | E6: =COUNTIF(Helpdesk_Tickets!I:I,"Open")+COUNTIF(Helpdesk_Tickets!I:I,"In Progress") | H6: =TEXT(COUNTIFS(Assets!L:L,"Yes",Assets!K:K,"<>Retired")/MAX(1,COUNTA(Assets!L2:L500)-COUNTIF(Assets!K:K,"Retired")),"0%")
B9: Avg Resolution (hrs) | E9: Licences Available | H9: Monthly Licence Cost
B10: =ROUND(AVERAGE(Helpdesk_Tickets!K:K),1) | E10: =SUM(Licenses!E:E) | H10: =TEXT(SUM(Licenses!I:I),"$#,##0")
B14: How to use: 1) Keep Assets, Helpdesk_Tickets and Licenses updated — the Dashboard recalculates itself. 2) Warranty column flags cover expiring in 90 days (amber) and expired (red). 3) Use the dropdowns — do not type statuses freehand. 4) Onboarding_Checklist tracks every new starter.

Sheet Assets
A1: Asset ID | B1: Device Type | C1: Brand / Model | D1: Serial Number | E1: Assigned To | F1: Department | G1: Location | H1: Purchase Date | I1: Warranty Expiry | J1: Warranty (days left) | K1: Status | L1: Intune Compliant
A2: AST-001 | B2: Laptop | C2: Dell Latitude 5540 | D2: DL5540-8841 | E2: A. Khan | F2: Finance | G2: Islamabad HQ | H2: 45363 | I2: 46458 | J2: =I2-TODAY() | K2: In Use | L2: Yes
A3: AST-002 | B3: Laptop | C3: HP EliteBook 840 G10 | D3: HP840-2210 | E3: S. Ahmed | F3: HR | G3: Islamabad HQ | H3: 45444 | I3: 46539 | J3: =I3-TODAY() | K3: In Use | L3: Yes
A4: AST-003 | B4: Laptop | C4: Lenovo ThinkPad T14 | D4: LT14-9034 | E4: Unassigned | F4: IT | G4: IT Store | H4: 45250 | I4: 46346 | J4: =I4-TODAY() | K4: In Stock | L4: Yes
A5: AST-004 | B5: Desktop | C5: Dell OptiPlex 7010 | D5: DO7010-117 | E5: M. Raza | F5: Operations | G5: Islamabad HQ | H5: 44971 | I5: 46067 | J5: =I5-TODAY() | K5: In Use | L5: Yes
A6: AST-005 | B6: Monitor | C6: Dell P2422H 24in | D6: DP24-5521 | E6: A. Khan | F6: Finance | G6: Islamabad HQ | H6: 45363 | I6: 46458 | J6: =I6-TODAY() | K6: In Use | L6: Yes
A7: AST-006 | B7: Laptop | C7: Dell Latitude 5540 | D7: DL5540-8850 | E7: F. Noor | F7: Marketing | G7: Remote | H7: 45540 | I7: 46635 | J7: =I7-TODAY() | K7: In Use | L7: No
A8: AST-007 | B8: Mobile | C8: Samsung Galaxy A54 | D8: SGA54-331 | E8: Field Team 1 | F8: Operations | G8: Field | H8: 45309 | I8: 46040 | J8: =I8-TODAY() | K8: In Use | L8: Yes
A9: AST-008 | B9: Printer | C9: HP LaserJet Pro M404 | D9: HPLJ-078 | E9: Shared — Floor 2 | F9: Admin | G9: Islamabad HQ | H9: 44803 | I9: 45899 | J9: =I9-TODAY() | K9: Under Repair | L9: Yes
A10: AST-009 | B10: Laptop | C10: HP ProBook 450 G9 | D10: HP450-664 | E10: R. Iqbal | F10: Finance | G10: Islamabad HQ | H10: 45068 | I10: 46164 | J10: =I10-TODAY() | K10: In Use | L10: Yes
A11: AST-010 | B11: Server | C11: Dell PowerEdge R750 | D11: DPR750-01 | E11: Data Centre | F11: IT | G11: Server Room | H11: 45108 | I11: 46935 | J11: =I11-TODAY() | K11: In Use | L11: Yes
A12: AST-011 | B12: Network Switch | C12: Cisco Catalyst 9200 | D12: CC9200-14 | E12: Network Rack A | F12: IT | G12: Server Room | H12: 45108 | I12: 46935 | J12: =I12-TODAY() | K12: In Use | L12: Yes
A13: AST-012 | B13: Laptop | C13: Lenovo IdeaPad 3 | D13: LI3-209 | E13: Unassigned | F13: IT | G13: IT Store | H13: 44296 | I13: 45392 | J13: =I13-TODAY() | K13: Retired | L13: No
... A21: AST-020 | B21: UPS | C21: APC Smart-UPS 1500 | D21: APC1500-07 | E21: Server Room | F21: IT | G21: Server Room | H21: 45442 | I21: 46537 | J21: =I21-TODAY() | K21: In Use | L21: Yes

Sheet Helpdesk_Tickets
A1: Ticket ID | B1: Date Logged | C1: Requester | D1: Department | E1: Category | F1: Priority | G1: Description | H1: Assigned Technician | I1: Status | J1: Resolution Date | K1: Resolution (hrs) | L1: SLA Breach (48h)
A2: TCK-1001 | B2: 46315 | C2: A. Khan | D2: Finance | E2: Microsoft 365 | F2: High | G2: Shared mailbox permissions not applying in Outlook | H2: Z. Yousaf | I2: Resolved | J2: 46315 | K2: 3.5 | L2: =IF(AND(K2<>"",K2>48),"YES","")
A3: TCK-1002 | B3: 46316 | C3: S. Ahmed | D3: HR | E3: Hardware | F3: Medium | G3: Laptop battery swelling — replacement required | H3: Z. Yousaf | I3: In Progress | L3: =IF(AND(K3<>"",K3>48),"YES","")
A4: TCK-1003 | B4: 46316 | C4: M. Raza | D4: Operations | E4: Network | F4: Critical | G4: VPN drops every 10 minutes for remote users | H4: Z. Yousaf | I4: Resolved | J4: 46317 | K4: 9 | L4: =IF(AND(K4<>"",K4>48),"YES","")
A5: TCK-1004 | B5: 46317 | C5: F. Noor | D5: Marketing | E5: Microsoft 365 | F5: Medium | G5: OneDrive sync conflicts on shared folder | H5: Support Team | I5: Resolved | J5: 46317 | K5: 2 | L5: =IF(AND(K5<>"",K5>48),"YES","")
A6: TCK-1005 | B6: 46317 | C6: R. Iqbal | D6: Finance | E6: Security | F6: High | G6: MFA prompt loop after password change | H6: Z. Yousaf | I6: Resolved | J6: 46318 | K6: 4.5 | L6: =IF(AND(K6<>"",K6>48),"YES","")
A7: TCK-1006 | B7: 46318 | C7: H. Tariq | D7: HR | E7: Access | F7: Medium | G7: New starter account and Intune enrolment | H7: Support Team | I7: Closed | J7: 46319 | K7: 6 | L7: =IF(AND(K7<>"",K7>48),"YES","")
A8: TCK-1007 | B8: 46318 | C8: Field Team 1 | D8: Operations | E8: Hardware | F8: Low | G8: Phone case and charger replacement | H8: Support Team | I8: Closed | J8: 46319 | K8: 1 | L8: =IF(AND(K8<>"",K8>48),"YES","")
A9: TCK-1008 | B9: 46319 | C9: Sales Team | D9: Sales | E9: Software | F9: Medium | G9: CRM client crashing on launch | H9: Z. Yousaf | I9: In Progress | L9: =IF(AND(K9<>"",K9>48),"YES","")
A10: TCK-1009 | B10: 46319 | C10: Design Desk | D10: Marketing | E10: Hardware | F10: Low | G10: Second monitor flickering at 60Hz | H10: Support Team | I10: Open | L10: =IF(AND(K10<>"",K10>48),"YES","")
A11: TCK-1010 | B11: 46320 | C11: Management | D11: Management | E11: Security | F11: Critical | G11: Conditional Access policy review after failed sign-ins | H11: Z. Yousaf | I11: In Progress | L11: =IF(AND(K11<>"",K11>48),"YES","")
A12: TCK-1011 | B12: 46320 | C12: A. Khan | D12: Finance | E12: Software | F12: Medium | G12: Excel reports slow on large workbook | H12: Support Team | I12: Resolved | J12: 46321 | K12: 3 | L12: =IF(AND(K12<>"",K12>48),"YES","")
A13: TCK-1012 | B13: 46321 | C13: Shared — Floor 2 | D13: Admin | E13: Hardware | F13: High | G13: Printer offline — print spooler fault | H13: Support Team | I13: Open | L13: =IF(AND(K13<>"",K13>48),"YES","")
A14: TCK-1013 | B14: 46321 | C14: S. Ahmed | D14: HR | E14: Microsoft 365 | F14: Low | G14: Teams meeting room calendar not visible | H14: Support Team | I14: Open | L14: =IF(AND(K14<>"",K14>48),"YES","")
A15: TCK-1014 | B15: 46321 | C15: M. Raza | D15: Operations | E15: Network | F15: Medium | G15: Wi-Fi dead spot in meeting room 2 | H15: Z. Yousaf | I15: In Progress | L15: =IF(AND(K15<>"",K15>48),"YES","")
A16: TCK-1015 | B16: 46322 | C16: New Starter | D16: HR | E16: Access | F16: Medium | G16: Onboarding — device, M365 licence and groups | H16: Z. Yousaf | I16: Open | L16: =IF(AND(K16<>"",K16>48),"YES","")

Sheet Licenses
A1: Software | B1: Vendor | C1: Licences Owned | D1: Assigned | E1: Available | F1: Utilisation % | G1: Renewal Date | H1: Cost / licence (USD/mo) | I1: Monthly Cost (USD) | J1: Status
A2: Microsoft 365 Business Premium | B2: Microsoft | C2: 85 | D2: 78 | E2: =C2-D2 | F2: =IF(C2=0,0,D2/C2) | G2: 46447 | H2: 22 | I2: =D2*H2 | J2: =IF(E2<=0,"FULL — renew / add",IF(E2<=5,"Low — plan renewal","OK"))
A3: Microsoft 365 Business Standard | B3: Microsoft | C3: 40 | D3: 34 | E3: =C3-D3 | F3: =IF(C3=0,0,D3/C3) | G3: 46447 | H3: 12.5 | I3: =D3*H3 | J3: =IF(E3<=0,"FULL — renew / add",IF(E3<=5,"Low — plan renewal","OK"))
A4: Windows Server 2022 (cores) | B4: Microsoft | C4: 16 | D4: 16 | E4: =C4-D4 | F4: =IF(C4=0,0,D4/C4) | G4: 46569 | H4: 90 | I4: =D4*H4 | J4: =IF(E4<=0,"FULL — renew / add",IF(E4<=5,"Low — plan renewal","OK"))
A5: Adobe Acrobat Pro | B5: Adobe | C5: 12 | D5: 10 | E5: =C5-D5 | F5: =IF(C5=0,0,D5/C5) | G5: 46371 | H5: 14.99 | I5: =D5*H5 | J5: =IF(E5<=0,"FULL — renew / add",IF(E5<=5,"Low — plan renewal","OK"))
A6: Antivirus — Endpoint Protection | B6: Vendor | C6: 120 | D6: 112 | E6: =C6-D6 | F6: =IF(C6=0,0,D6/C6) | G6: 46418 | H6: 3.5 | I6: =D6*H6 | J6: =IF(E6<=0,"FULL — renew / add",IF(E6<=5,"Low — plan renewal","OK"))
A7: Backup & Recovery Agents | B7: Vendor | C7: 30 | D7: 27 | E7: =C7-D7 | F7: =IF(C7=0,0,D7/C7) | G7: 46537 | H7: 8 | I7: =D7*H7 | J7: =IF(E7<=0,"FULL — renew / add",IF(E7<=5,"Low — plan renewal","OK"))

Sheet Onboarding_Checklist
A1: New Starter Onboarding — IT Checklist
A2: Task | B2: Owner | C2: Status | D2: Notes
A3: Create Microsoft 365 account & assign licence | B3: IT | C3: Done
A4: Add user to security groups & shared mailboxes | B4: IT | C4: Done
A5: Enrol device in Intune & apply compliance policy | B5: IT | C5: Done
A6: Configure MFA & Conditional Access | B6: IT | C6: In Progress
A7: Install standard apps (Office, Teams, VPN) | B7: IT | C7: In Progress
A8: Hand over device & asset sign-off (Assets sheet) | B8: IT / HR | C8: Not Started
A9: Security awareness briefing & password policy | B9: IT | C9: Not Started
A10: Add to HR system & payroll | B10: HR | C10: Done
A11: Manager intro & first-week plan | B11: HR / Manager | C11: Not Started

Sheet Summary
A1: Ticket Status | B1: Count
A2: Open | B2: =COUNTIF(Helpdesk_Tickets!I:I,A2)
A3: In Progress | B3: =COUNTIF(Helpdesk_Tickets!I:I,A3)
A4: Resolved | B4: =COUNTIF(Helpdesk_Tickets!I:I,A4)
A5: Closed | B5: =COUNTIF(Helpdesk_Tickets!I:I,A5)
A7: Asset Status | B7: Count
A8: In Use | B8: =COUNTIF(Assets!K:K,A8)
A9: In Stock | B9: =COUNTIF(Assets!K:K,A9)
A10: Under Repair | B10: =COUNTIF(Assets!K:K,A10)
A11: Retired | B11: =COUNTIF(Assets!K:K,A11)
